lists/__init__.py
lists/list_manager.py
tests/__init__.py
tests/test_lists.py
list_manager-1.0.0.dist-info/LICENSE
list_manager-1.0.0.dist-info/METADATA
list_manager-1.0.0.dist-info/WHEEL
list_manager-1.0.0.dist-info/entry_points.txt
list_manager-1.0.0.dist-info/top_level.txt
list_manager-1.0.0.dist-info/RECORD
