Metadata-Version: 2.1
Name: list-manager
Version: 1.0.0
Summary: A simple CLI tool that allows management of lists
Home-page: https://github.com/nairraghav/lists-library
Author: Raghav Nair
Author-email: nairraghav@hotmail.com
License: UNKNOWN
Platform: UNKNOWN
Classifier: Programming Language :: Python :: 3
Classifier: License :: OSI Approved :: MIT License
Classifier: Operating System :: OS Independent
Requires-Python: >=3.6
